vendi/__init__.py
vendi/completions/__init__.py
vendi/completions/completions.py
vendi/completions/schema.py
vendi/core/__init__.py
vendi/core/ahttp_client.py
vendi/core/config.py
vendi/core/http_client.py
vendi/core/schema.py
vendi/datasets/__init__.py
vendi/datasets/datasets.py
vendi/datasets/schema.py
vendi/deployments/__init__.py
vendi/deployments/deployments.py
vendi/deployments/schema.py
vendi/finetune/__init__.py
vendi/finetune/finetune.py
vendi/finetune/schema.py
vendi/models/__init__.py
vendi/models/models.py
vendi/models/schema.py
vendi-0.1.24.dist-info/METADATA
vendi-0.1.24.dist-info/WHEEL
vendi-0.1.24.dist-info/RECORD
